lda11/__init__.py
lda11/_lda.cpython-39-darwin.so
lda11/_lda.pyi
lda11/labelled_lda.py
lda11/lda.py
lda11/util.py
lda11-0.3.0.2.dist-info/METADATA
lda11-0.3.0.2.dist-info/WHEEL
lda11-0.3.0.2.dist-info/top_level.txt
lda11-0.3.0.2.dist-info/RECORD
