Metadata-Version: 2.1
Name: lda11
Version: 0.3.0.2
Summary: Yet another CGS sampler for Latent Dirichlet Allocation.
Home-page: https://github.com/tohtsky/lda11
Author: Tomoki Ohtsuki
Author-email: tomoki.ohtsuki.19937@outook.jp
License: UNKNOWN
Platform: UNKNOWN
Requires-Dist: numpy (>=1.21)
Requires-Dist: tqdm
Requires-Dist: scipy (>=1.0.0)
Requires-Dist: typing-extensions (>=3.10)
